{
	"configurations" : 
	[
		{
			"directories" : 
			[
				{
					"build" : ".",
					"jsonFile" : "directory-.-Debug-d0094a50bb2071803777.json",
					"minimumCMakeVersion" : 
					{
						"string" : "3.27"
					},
					"projectIndex" : 0,
					"source" : ".",
					"targetIndexes" : 
					[
						0
					]
				}
			],
			"name" : "Debug",
			"projects" : 
			[
				{
					"directoryIndexes" : 
					[
						0
					],
					"name" : "0_1_build_adjacency_matrix",
					"targetIndexes" : 
					[
						0
					]
				}
			],
			"targets" : 
			[
				{
					"directoryIndex" : 0,
					"id" : "0_1_build_adjacency_matrix::@6890427a1f51a3e7e1df",
					"jsonFile" : "target-0_1_build_adjacency_matrix-Debug-392cc9f70529b482a8a6.json",
					"name" : "0_1_build_adjacency_matrix",
					"projectIndex" : 0
				}
			]
		}
	],
	"kind" : "codemodel",
	"paths" : 
	{
		"build" : "C:/Users/qRe/CLionProjects/algorithms_and_data_structures/Graphs/0_1_build_adjacency_matrix/cmake-build-debug",
		"source" : "C:/Users/qRe/CLionProjects/algorithms_and_data_structures/Graphs/0_1_build_adjacency_matrix"
	},
	"version" : 
	{
		"major" : 2,
		"minor" : 6
	}
}
